unica_globopt/ADS.py
unica_globopt/__init__.py
unica_globopt/nn_utils.py
unica_globopt/active_subspaces/__init__.py
unica_globopt/active_subspaces/domains.py
unica_globopt/active_subspaces/gradients.py
unica_globopt/active_subspaces/integrals.py
unica_globopt/active_subspaces/optimizers.py
unica_globopt/active_subspaces/response_surfaces.py
unica_globopt/active_subspaces/subspaces.py
unica_globopt/active_subspaces/utils/__init__.py
unica_globopt/active_subspaces/utils/designs.py
unica_globopt/active_subspaces/utils/misc.py
unica_globopt/active_subspaces/utils/plotters.py
unica_globopt/active_subspaces/utils/qp_solver.py
unica_globopt/active_subspaces/utils/quadrature.py
unica_globopt/active_subspaces/utils/response_surfaces.py
unica_globopt/active_subspaces/utils/simrunners.py
unica_globopt-0.0.21.dist-info/LICENCE
unica_globopt-0.0.21.dist-info/METADATA
unica_globopt-0.0.21.dist-info/WHEEL
unica_globopt-0.0.21.dist-info/top_level.txt
unica_globopt-0.0.21.dist-info/RECORD
