Metadata-Version: 2.1
Name: unica-globopt
Version: 0.0.21
Summary: Global Optimisation Through AI-Enabled Active Subspaces
Home-page: https://github.com/pypa/sampleproject
Author: Diego I. Lopez
Author-email: diegoi.lopez@unica.it
License: UNKNOWN
Project-URL: Bug Tracker, https://github.com/pypa/sampleproject/issues
Platform: UNKNOWN
Classifier: Programming Language :: Python :: 3
Classifier: License :: OSI Approved :: MIT License
Classifier: Operating System :: OS Independent
Requires-Python: >=3.6
License-File: LICENCE
